energy_flexibility_kpis/__init__.py
energy_flexibility_kpis/test/__init__.py
energy_flexibility_kpis-0.0.0.data/data/requirements/requirements.txt
energy_flexibility_kpis-0.0.0.dist-info/LICENSE
energy_flexibility_kpis-0.0.0.dist-info/METADATA
energy_flexibility_kpis-0.0.0.dist-info/WHEEL
energy_flexibility_kpis-0.0.0.dist-info/top_level.txt
energy_flexibility_kpis-0.0.0.dist-info/RECORD
