Metadata-Version: 2.1
Name: energy-flexibility-kpis
Version: 0.0.0
Summary: Python package for the computation of energy flexibility KPIs
Home-page: https://github.com/HichamJohra/energy_flexibility_kpis
Author: Hicham Johra
Author-email: hj@build.aau.dk
Project-URL: Bug Tracker, https://github.com/HichamJohra/energy_flexibility_kpis/issues
Project-URL: Documentation, https://github.com/HichamJohra/energy_flexibility_kpis
Project-URL: Source Code, https://github.com/HichamJohra/energy_flexibility_kpis
Requires-Python: >=3.9
License-File: LICENSE
Provides-Extra: dev
Requires-Dist: setuptools (>=42) ; extra == 'dev'
Requires-Dist: wheel ; extra == 'dev'
Requires-Dist: pytest ; extra == 'dev'
Requires-Dist: pytest-cov ; extra == 'dev'
Requires-Dist: pytest-xdist ; extra == 'dev'
